LICENSE
MANIFEST.in
README.md
setup.cfg
setup.py
botasaurus_driver/__init__.py
botasaurus_driver/base_data.py
botasaurus_driver/beep_utils.py
botasaurus_driver/driver.py
botasaurus_driver/driver_utils.py
botasaurus_driver/exceptions.py
botasaurus_driver/lang.py
botasaurus_driver/local_storage_driver.py
botasaurus_driver/opponent.py
botasaurus_driver/profile.py
botasaurus_driver/solve_cloudflare_captcha.py
botasaurus_driver/tiny_profile.py
botasaurus_driver/user_agent.py
botasaurus_driver/window_size.py
botasaurus_driver.egg-info/PKG-INFO
botasaurus_driver.egg-info/SOURCES.txt
botasaurus_driver.egg-info/dependency_links.txt
botasaurus_driver.egg-info/requires.txt
botasaurus_driver.egg-info/top_level.txt
botasaurus_driver/cdp/README.md
botasaurus_driver/cdp/__init__.py
botasaurus_driver/cdp/accessibility.py
botasaurus_driver/cdp/animation.py
botasaurus_driver/cdp/audits.py
botasaurus_driver/cdp/autofill.py
botasaurus_driver/cdp/background_service.py
botasaurus_driver/cdp/browser.py
botasaurus_driver/cdp/cache_storage.py
botasaurus_driver/cdp/cast.py
botasaurus_driver/cdp/console.py
botasaurus_driver/cdp/css.py
botasaurus_driver/cdp/database.py
botasaurus_driver/cdp/debugger.py
botasaurus_driver/cdp/device_access.py
botasaurus_driver/cdp/device_orientation.py
botasaurus_driver/cdp/dom.py
botasaurus_driver/cdp/dom_debugger.py
botasaurus_driver/cdp/dom_snapshot.py
botasaurus_driver/cdp/dom_storage.py
botasaurus_driver/cdp/emulation.py
botasaurus_driver/cdp/event_breakpoints.py
botasaurus_driver/cdp/fed_cm.py
botasaurus_driver/cdp/fetch.py
botasaurus_driver/cdp/headless_experimental.py
botasaurus_driver/cdp/heap_profiler.py
botasaurus_driver/cdp/indexed_db.py
botasaurus_driver/cdp/input_.py
botasaurus_driver/cdp/inspector.py
botasaurus_driver/cdp/io.py
botasaurus_driver/cdp/layer_tree.py
botasaurus_driver/cdp/log.py
botasaurus_driver/cdp/media.py
botasaurus_driver/cdp/memory.py
botasaurus_driver/cdp/network.py
botasaurus_driver/cdp/overlay.py
botasaurus_driver/cdp/page.py
botasaurus_driver/cdp/performance.py
botasaurus_driver/cdp/performance_timeline.py
botasaurus_driver/cdp/preload.py
botasaurus_driver/cdp/profiler.py
botasaurus_driver/cdp/py.typed
