Metadata-Version: 2.1
Name: botasaurus_driver
Version: 4.0.53
Summary: Super Fast, Super Anti-Detect, and Super Intuitive Web Driver
Home-page: https://github.com/omkarcloud/botasaurus-driver
Author: Chetan
Author-email: chetan@omkar.cloud
Maintainer: Chetan
Maintainer-email: chetan@omkar.cloud
License: MIT
Project-URL: Homepage, https://github.com/omkarcloud/botasaurus-driver
Project-URL: Bug Reports, https://github.com/omkarcloud/botasaurus-driver/issues
Project-URL: Source, https://github.com/omkarcloud/botasaurus-driver
Keywords: webdriver,browser,captcha,web-scraping,selenium,navigator,python3,cloudflare,anti-delect,anti-bot,bot-detection,cloudflare-bypass,distil,anti-detection
Classifier: Development Status :: 3 - Alpha
Classifier: Intended Audience :: Developers
Classifier: License :: OSI Approved :: MIT License
Classifier: Topic :: Internet :: WWW/HTTP :: Browsers
Classifier: Programming Language :: Python :: 3.7
Classifier: Programming Language :: Python :: 3.8
Classifier: Programming Language :: Python :: 3.9
Classifier: Programming Language :: Python :: 3.10
Classifier: Programming Language :: Python :: 3.11
Requires-Python: >=3.5
License-File: LICENSE
Requires-Dist: requests
Requires-Dist: deprecated
Requires-Dist: psutil
Requires-Dist: botasaurus-proxy-authentication
Requires-Dist: websocket-client>=1.8.0
Requires-Dist: pyvirtualdisplay
